CHANGELOG.md
CONTRIBUTING.md
README.md
docs/changelog.md
docs/contributing.md
docs/index.md
docs/library.md
docs/license.md
ssh2_parse_key/__init__.py
ssh2_parse_key/ssh2_parse_key.py
tests/__init__.py
tests/test_convert_public_key.py
tests/test_handle_crlf_line_ends.py
tests/test_load_keys_with_comments.py
tests/test_load_multiple_key.py
tests/test_load_multiple_short.py
tests/test_load_private_key.py
tests/test_no_valid_keys.py
tests/test_openssh_public_key_load.py
tests/test_rfc4716_public_key_load.py
ssh2_parse_key-0.8.0.dist-info/LICENSE
ssh2_parse_key-0.8.0.dist-info/METADATA
ssh2_parse_key-0.8.0.dist-info/WHEEL
ssh2_parse_key-0.8.0.dist-info/RECORD
