Metadata-Version: 2.1
Name: ssh2_parse_key
Version: 0.8.0
Summary: Parses ssh2 keys and converts to multiple formats.
Home-page: https://pypi.org/project/ssh2-parse-key/
License: MIT
Author: Nigel Metheringham
Author-email: nigelm@cpan.org
Requires-Python: >=3.8,<4.0
Classifier: Development Status :: 2 - Pre-Alpha
Classifier: Intended Audience :: Developers
Classifier: License :: OSI Approved :: BSD License
Classifier: License :: OSI Approved :: MIT License
Classifier: Natural Language :: English
Classifier: Programming Language :: Python :: 3
Classifier: Programming Language :: Python :: 3.8
Classifier: Programming Language :: Python :: 3.9
Classifier: Programming Language :: Python :: 3.10
Classifier: Programming Language :: Python :: 3.11
Classifier: Programming Language :: Python :: 3.12
Classifier: Programming Language :: Python :: 3.6
Classifier: Programming Language :: Python :: 3.7
Classifier: Topic :: Software Development :: Libraries :: Python Modules
Requires-Dist: attrs (>=20.2.0)
Project-URL: Documentation, https://nigelm.github.io/ssh2_parse_key/
Project-URL: Repository, https://github.com/nigelm/ssh2_parse_key
